setup.cfg
setup.py
elastic_dict.egg-info/PKG-INFO
elastic_dict.egg-info/SOURCES.txt
elastic_dict.egg-info/dependency_links.txt
elastic_dict.egg-info/top_level.txt
elasticdict/ElasticDict.py
elasticdict/__init__.py