Metadata-Version: 1.1
Name: elastic-dict
Version: 0.6
Summary: Subclass of dict() for preparing large nested structures
Home-page: https://github.com/KokocGroup/elastic-dict
Author: Alexey Ruzin
Author-email: ruzin@kokoc.com
License: UNKNOWN
Download-URL: https://github.com/KokocGroup/elastic-dict/tarball/v0.6
Keywords: dict,dictionary,django,template
Platform: UNKNOWN
